tc_scraper/__init__.py
tc_scraper/__main__.py
tc_scraper/topcoder_scraper.py
tc_scraper-0.2.dist-info/LICENSE.md
tc_scraper-0.2.dist-info/METADATA
tc_scraper-0.2.dist-info/WHEEL
tc_scraper-0.2.dist-info/entry_points.txt
tc_scraper-0.2.dist-info/top_level.txt
tc_scraper-0.2.dist-info/RECORD
