Metadata-Version: 2.1
Name: tc-scraper
Version: 0.2
Summary: Software Project
Home-page: https://github.com/y0g38h-kum4r/tc_scraper
Author: y0g38h-kum4r
Author-email: yogeshkumar.m200010@gmail.com
License: UNKNOWN
Keywords: Software
Platform: UNKNOWN
Classifier: License :: OSI Approved :: MIT License
Classifier: Programming Language :: Python :: 3
Classifier: Operating System :: OS Independent
License-File: LICENSE.md
Requires-Dist: beautifulsoup4 (>=4.9.3)
Requires-Dist: lxml (>=4.6.3)
Requires-Dist: requests (>=2.25.1)
